synspark_logger/__init__.py
synspark_logger/api.py
synspark_logger/filter.py
synspark_logger/output.py
synspark_logger/backend/__init__.py
synspark_logger/backend/files.py
synspark_logger/backend/systemctl.py
synspark_logger/install/__init__.py
synspark_logger/install/files/__init__.py
synspark_logger/install/files/synspark_logger.service.py
synspark_logger-1.1.12.data/data/etc/synspark_logger/synspark_logger.cfg
synspark_logger-1.1.12.data/data/usr/share/doc/synspark_logger/README.rst
synspark_logger-1.1.12.data/scripts/synspark-logger
synspark_logger-1.1.12.dist-info/DESCRIPTION.rst
synspark_logger-1.1.12.dist-info/METADATA
synspark_logger-1.1.12.dist-info/RECORD
synspark_logger-1.1.12.dist-info/WHEEL
synspark_logger-1.1.12.dist-info/metadata.json
synspark_logger-1.1.12.dist-info/top_level.txt
