Metadata-Version: 2.0
Name: synspark-logger
Version: 1.1.12
Summary: Collect your security events to allow you to visualize it on Synspark.
Home-page: https://www.synspark.com
Author: Synspark
Author-email: matthieu.chevrier@synhack.fr
License: UNKNOWN
Platform: Posix
Classifier: Development Status :: 3 - Alpha
Classifier: Environment :: Console
Classifier: Intended Audience :: Developers
Classifier: Intended Audience :: System Administrators
Classifier: Topic :: Internet :: Log Analysis
Classifier: Topic :: Security
Classifier: Topic :: System :: Logging
Classifier: Programming Language :: Python :: 2
Classifier: Programming Language :: Python :: 2.7
Classifier: Programming Language :: Python :: 3
Classifier: Programming Language :: Python :: 3.2
Classifier: Programming Language :: Python :: 3.3
Classifier: Programming Language :: Python :: 3.4
Requires-Dist: requests
